README.txt
setup.py
django_templateinspector.egg-info/PKG-INFO
django_templateinspector.egg-info/SOURCES.txt
django_templateinspector.egg-info/dependency_links.txt
django_templateinspector.egg-info/entry_points.txt
django_templateinspector.egg-info/not-zip-safe
django_templateinspector.egg-info/top_level.txt
djtemplateinspector/__init__.py