Metadata-Version: 1.0
Name: django-templateinspector
Version: 0.1
Summary: Find out what context variables are expected by a Django Template
Home-page: UNKNOWN
Author: Ethan Jucovy
Author-email: ejucovy@gmail.com
License: BSD
Platform: UNKNOWN
